pynotify/__init__.py
pynotify/__main__.py
pynotify/config.py
pynotify/pynotify.py
pynotify_telfer-0.0.2.dist-info/LICENSE
pynotify_telfer-0.0.2.dist-info/METADATA
pynotify_telfer-0.0.2.dist-info/WHEEL
pynotify_telfer-0.0.2.dist-info/entry_points.txt
pynotify_telfer-0.0.2.dist-info/top_level.txt
pynotify_telfer-0.0.2.dist-info/RECORD
