Metadata-Version: 2.1
Name: pynotify-telfer
Version: 0.0.2
Summary: Simple email notifications
Home-page: https://github.com/A-Telfer/simple-notification-script
Author: Andre Telfer
Author-email: andretelfer@cmail.carleton.ca
License: UNKNOWN
Project-URL: Bug Tracker, https://github.com/A-Telfer/simple-notification-script/issues
Platform: UNKNOWN
Classifier: Programming Language :: Python :: 3
Classifier: License :: OSI Approved :: MIT License
Classifier: Operating System :: OS Independent
Requires-Python: >=3.6
License-File: LICENSE
Requires-Dist: click
Requires-Dist: pyyaml
